pwnscripts/__init__.py
pwnscripts/config.py
pwnscripts/context.py
pwnscripts/elf.py
pwnscripts/libcdb_query.py
pwnscripts/rop.py
pwnscripts/uncommon.py
pwnscripts/util.py
pwnscripts/fsb/__init__.py
pwnscripts/fsb/find_offset.py
pwnscripts/fsb/leak.py
pwnscripts-0.6.0.dist-info/LICENSE
pwnscripts-0.6.0.dist-info/METADATA
pwnscripts-0.6.0.dist-info/WHEEL
pwnscripts-0.6.0.dist-info/top_level.txt
pwnscripts-0.6.0.dist-info/RECORD
