Metadata-Version: 2.1
Name: pwnscripts
Version: 0.6.0
Summary: Simple pwntools QoL scripts
Home-page: https://github.com/152334H/pwnscripts
Author: 152334H
Author-email: 54623771+152334H@users.noreply.github.com
License: GPL3
Platform: UNKNOWN
Classifier: Development Status :: 3 - Alpha
Classifier: Environment :: Console
Classifier: Intended Audience :: Developers
Classifier: Intended Audience :: System Administrators
Classifier: Natural Language :: English
Classifier: Operating System :: POSIX :: Linux
Classifier: Programming Language :: Python :: 3.8
Classifier: Topic :: Security
Classifier: Topic :: Software Development :: Debuggers
Classifier: Topic :: Utilities
Requires-Python: >=3.8
Requires-Dist: pwntools
